MUSiCC-1.0.4.data/scripts/run_musicc.py
MUSiCC-1.0.4.data/scripts/test_musicc.py
musicc/__init__.py
musicc/core.py
musicc/data/Correlog_clusters_genes_DATA_HMP_STOOL_CLASS_HMP_SAMP_134_KO_76.tab
musicc/data/Final_Betas_ALL_SAMPLES_DATA_HMP_STOOL_CLASS_HMP_SAMP_134_KO_76.tab
musicc/data/Gene_level_features_for_all_KOs_DATA_HMP_STOOL_CLASS_HMP_SAMP_134_KO_76.tab
musicc/data/semi_uscg_72_kegg_min_2148_max_2313.lst
musicc/data/uscg_76_kegg_min_2313.lst
musicc/examples/simulated_ko_MUSiCC_Normalized.tab
musicc/examples/simulated_ko_MUSiCC_Normalized_Corrected_learn_model.tab
musicc/examples/simulated_ko_MUSiCC_Normalized_Corrected_use_generic.tab
musicc/examples/simulated_ko_relative_abundance.tab
MUSiCC-1.0.4.dist-info/AUTHORS.rst
MUSiCC-1.0.4.dist-info/LICENSE
MUSiCC-1.0.4.dist-info/METADATA
MUSiCC-1.0.4.dist-info/WHEEL
MUSiCC-1.0.4.dist-info/top_level.txt
MUSiCC-1.0.4.dist-info/RECORD
