Metadata-Version: 2.1
Name: MUSiCC
Version: 1.0.4
Summary: MUSICC: A marker genes based framework for metagenomic normalization and accurate profiling of gene abundances in the microbiome.
Home-page: http://elbo.gs.washington.edu/software_musicc.html
Author: Ohad Manor
Author-email: omanor@gmail.com
License: ['BSD']
Platform: UNKNOWN
Classifier: License :: OSI Approved :: BSD License
Requires-Dist: NumPy (>=1.17.0)
Requires-Dist: SciPy (>=1.3.0)
Requires-Dist: scikit-learn (>=0.21.3)
Requires-Dist: pandas (>=0.25.0)
